{
  "parent": "minecraft:recipes/root",
  "rewards": {
    "recipes": [
      "natura:world/wood/amaranth/planks"
    ]
  },
  "criteria": {
    "has_log": {
      "trigger": "minecraft:inventory_changed",
      "conditions": {
        "items": [
          {
            "tag": "natura:amaranth_logs"
          }
        ]
      }
    },
    "has_the_recipe": {
      "trigger": "minecraft:recipe_unlocked",
      "conditions": {
        "recipe": "natura:world/wood/amaranth/planks"
      }
    }
  },
  "requirements": [
    [
      "has_log",
      "has_the_recipe"
    ]
  ]
}